MANIFEST.in
README.md
setup.cfg
setup.py
third-party/flat_hash_map.hpp
yack/__init__.py
yack.egg-info/PKG-INFO
yack.egg-info/SOURCES.txt
yack.egg-info/dependency_links.txt
yack.egg-info/entry_points.txt
yack.egg-info/requires.txt
yack.egg-info/top_level.txt
yack/cli/__init__.py
yack/cli/_cli.py
yack/core/__init__.py
yack/core/_core.py
yack/ext/__init__.py
yack/ext/count.cpp
yack/ext/count.h
yack/ext/count.pxd
yack/ext/count.pyx