Metadata-Version: 1.0
Name: yack
Version: 0.1.2
Summary: Yet another k-mer counter
Home-page: https://github.com/arriam-lab2/yack
Author: Nikolay Romashchenko
Author-email: nikolay.romashchenko@gmail.com
License: MIT
Keywords: k-mer,counting
Platform: UNKNOWN
